agrid/__init__.py
agrid/acc.py
agrid/features.py
agrid/grid.py
agrid/strat.py
agrid-0.3.9.7.dist-info/LICENSE
agrid-0.3.9.7.dist-info/METADATA
agrid-0.3.9.7.dist-info/WHEEL
agrid-0.3.9.7.dist-info/top_level.txt
agrid-0.3.9.7.dist-info/RECORD
