Metadata-Version: 2.1
Name: agrid
Version: 0.3.9.7
Summary: A grid for spatial multidimensional processing
Home-page: https://github.com/TobbeTripitaka/agrid
Author: Tobias Staal
Author-email: tobbetripitaka@gmail.com
License: UNKNOWN
Platform: UNKNOWN
Classifier: Programming Language :: Python :: 3
Classifier: License :: OSI Approved :: MIT License
Classifier: Operating System :: OS Independent
Requires-Python: >=3.6
Requires-Dist: Cartopy (>=0.17.0)
Requires-Dist: dask (>=2.5.1)
Requires-Dist: numpy (>=1.17.2tqdm>=4.36.1)
Requires-Dist: requests (>=2.22.0)
Requires-Dist: geopandas (>=0.6.1)
Requires-Dist: imageio (>=2.6.0)
Requires-Dist: rasterio (>=1.0.21)
Requires-Dist: scipy (>=1.3.1)
Requires-Dist: xarray (>=0.14.1)
